apd_crs/__init__.py
apd_crs/_common_estimate.py
apd_crs/_core.py
apd_crs/_estimate.py
apd_crs/_parameters.py
apd_crs/_survival_func.py
apd_crs/_validate.py
apd_crs/survival_analysis.py
apd_crs/datasets/Telco-Customer-Churn.csv
apd_crs/datasets/__init__.py
apd_crs/datasets/advertising.csv
apd_crs/datasets/load_datasets.py
apd_crs/datasets/manufacturing.csv
apd_crs/datasets/melanoma.csv
apd_crs-0.1.0.dist-info/LICENSE
apd_crs-0.1.0.dist-info/METADATA
apd_crs-0.1.0.dist-info/WHEEL
apd_crs-0.1.0.dist-info/top_level.txt
apd_crs-0.1.0.dist-info/RECORD
