Metadata-Version: 2.1
Name: apd-crs
Version: 0.1.0
Summary: apd-crs is a Python package for survival analysis with cure rate, released by Aimpoint Digital, LP
Home-page: https://github.com/Aimpoint-Digital/apd-crs
Author: Yash Puranik
Author-email: yash.puranik@aimpointdigital.com
License: UNKNOWN
Project-URL: Bug Tracker, https://github.com/Aimpoint-Digital/apd-crs/issues
Platform: UNKNOWN
Classifier: Programming Language :: Python :: 3
Classifier: License :: OSI Approved :: GNU General Public License v3 (GPLv3)
Classifier: Operating System :: OS Independent
Requires-Python: >=3.6
License-File: LICENSE
Requires-Dist: numpy
Requires-Dist: scipy
Requires-Dist: autograd
Requires-Dist: pandas
Requires-Dist: scikit-survival
Requires-Dist: scikit-learn
Requires-Dist: tqdm
